zen3geo/__init__.py
zen3geo/datapipes/__init__.py
zen3geo/datapipes/datashader.py
zen3geo/datapipes/geopandas.py
zen3geo/datapipes/pyogrio.py
zen3geo/datapipes/pystac.py
zen3geo/datapipes/pystac_client.py
zen3geo/datapipes/rioxarray.py
zen3geo/datapipes/stackstac.py
zen3geo/datapipes/xbatcher.py
zen3geo/datapipes/xpystac.py
zen3geo-0.6.2.dist-info/LICENSE.md
zen3geo-0.6.2.dist-info/METADATA
zen3geo-0.6.2.dist-info/WHEEL
zen3geo-0.6.2.dist-info/RECORD
